python/__init__.py
python/_version.py
python/nt_entry.py
python/nt_entry_banded.py
python/ntc_entry.py
python/misc/__init__.py
python/misc/collectMetrics.py
python/misc/compareDatasets.py
python/misc/compareTools.py
python/misc/csv_to_ms_heatmap.py
python/misc/csv_to_tex.py
python/misc/edgeDetection.py
python/misc/evaluateReads.py
python/misc/evaluateSubsequentTools.py
python/misc/extractDoradoMoves.py
python/misc/segToFasta.py
python/misc/tomboToFasta.py
python/plot/__init__.py
python/plot/plotSegmentation.py
python/plot/plotToolSegments.py
python/plot/plotTrainedParams.py
python/segmentation/FileIO.py
python/segmentation/__init__.py
python/segmentation/segment.py
python/segmentation/train.py
bin/dynamont-NT
bin/dynamont-NT-banded
bin/dynamont-NTC
models/dna/r10.4.1/dna_r10.4.1_e8.2_260bps.model
models/dna/r10.4.1/dna_r10.4.1_e8.2_400bps.model
models/rna/r9.4.1/rna002_5mer.model
models/rna/rp4/rna004_9mer.model
dynamont-0.7.2.dist-info/METADATA
dynamont-0.7.2.dist-info/WHEEL
dynamont-0.7.2.dist-info/entry_points.txt
dynamont-0.7.2.dist-info/licenses/LICENSE
dynamont-0.7.2.dist-info/RECORD
