Metadata-Version: 2.4
Name: dynamont
Version: 0.7.2
Summary: Segmentation/resquiggling tool for ONT signals.
Project-URL: repository, https://github.com/rnajena/dynamont
Author-email: Jannes Spangenberg <jannes.spangenberg@uni-jena.de>
License: GNUv3
License-File: LICENSE
Classifier: Intended Audience :: Science/Research
Classifier: License :: OSI Approved :: GNU General Public License v3 (GPLv3)
Classifier: Programming Language :: Python
Classifier: Programming Language :: Python :: 3 :: Only
Classifier: Programming Language :: Python :: 3.10
Classifier: Programming Language :: Python :: 3.11
Classifier: Programming Language :: Python :: 3.12
Classifier: Topic :: Scientific/Engineering :: Bio-Informatics
Requires-Python: >=3.10
Requires-Dist: matplotlib>=3.2.0
Requires-Dist: numpy>=1.26.0
Requires-Dist: pandas>=2.2.0
Requires-Dist: psutil>=6.0.0
Requires-Dist: pysam>=0.22.0
Requires-Dist: read5-ont>=1.2.8
Requires-Dist: seaborn>=0.13.0
Provides-Extra: test
Requires-Dist: mypy; extra == 'test'
Requires-Dist: pytest; extra == 'test'
Requires-Dist: pytest-cov; extra == 'test'
Requires-Dist: pytest-mock; extra == 'test'
